botfriend/__init__.py
botfriend/bot.py
botfriend/config.py
botfriend/feedbridge.py
botfriend/model.py
botfriend/scripts.py
botfriend/testing.py
botfriend/util.py
botfriend/publish/__init__.py
botfriend/publish/_mastodon.py
botfriend/publish/atom.py
botfriend/publish/echo.py
botfriend/publish/file.py
botfriend/publish/podcast.py
botfriend/publish/tumblr.py
botfriend/publish/twitter.py
botfriend/tests/__init__.py
botfriend/tests/test_bot.py
botfriend/tests/test_model.py
bots/__init__.py
bots/a-dull-bot/__init__.py
bots/almanac/__init__.py
bots/ama/__init__.py
bots/anniversary/__init__.py
bots/best-of-rhp/__init__.py
bots/boat-names/__init__.py
bots/bot-of-mormon/__init__.py
bots/bot-of-mormon/mormon.py
bots/conways-lives/__init__.py
bots/crowd-board-games/__init__.py
bots/crowd-video-games/__init__.py
bots/euphemism/__init__.py
bots/euphemism/euphemism.py
bots/everybrendan/__init__.py
bots/frances-daily/__init__.py
bots/fusion/__init__.py
bots/fusion/fusion.py
bots/ghostbusters/__init__.py
bots/ghostbusters/ghostbusters.py
bots/hapax-hegemon/__init__.py
bots/ingsoc-slogans/__init__.py
bots/joe-miller/__init__.py
bots/junkmail/__init__.py
bots/junkmail/page.py
bots/limericks/__init__.py
bots/limericks/limerick.py
bots/link-relations/__init__.py
bots/mashteroids/__init__.py
bots/mashteroids/mashteroids.py
bots/minecraft-ebooks/__init__.py
bots/minecraft-signs/__init__.py
bots/minecraft-signs/setup.py
bots/podcast/__init__.py
bots/podcast/dump-some-titles.py
bots/podcast/gather-some-info.py
bots/podcast/podcast.py
bots/pony-strategies/__init__.py
bots/postcards/__init__.py
bots/roller-derby/__init__.py
bots/sbotus/__init__.py
bots/sbotus/argument.py
bots/secretly-public-domain/__init__.py
bots/serial-entrepreneur/__init__.py
bots/serial-entrepreneur/entrepreneur.py
bots/smooth-unicode/__init__.py
bots/time-magazine/__init__.py
bots/time-magazine/fix_script.py
bots/time-magazine/old.py
bots/yearbooks/__init__.py
bots/yearbooks/ia.py
bots/yearbooks/page.py
botfriend-0.7.0.dist-info/LICENSE
botfriend-0.7.0.dist-info/METADATA
botfriend-0.7.0.dist-info/WHEEL
botfriend-0.7.0.dist-info/entry_points.txt
botfriend-0.7.0.dist-info/top_level.txt
botfriend-0.7.0.dist-info/RECORD
