Metadata-Version: 2.1
Name: botfriend
Version: 0.7.0
Summary: A server-side framework that makes it easy to manage artistic bots that post to social media.
Home-page: https://github.com/leonardr/botfriend/
Author: Leonard Richardson
Author-email: leonardr@segfault.org
License: MIT
Platform: UNKNOWN
Classifier: License :: OSI Approved :: MIT License
Classifier: Programming Language :: Python :: 2
Classifier: Programming Language :: Python :: 3
Classifier: Programming Language :: Python :: Implementation :: CPython
Classifier: Topic :: Text Processing
Classifier: Topic :: Artistic Software
Requires-Dist: Mastodon.py (>=1.3.1)
Requires-Dist: TextBlob
Requires-Dist: beautifulsoup4
Requires-Dist: feedgen
Requires-Dist: feedparser
Requires-Dist: nose
Requires-Dist: olipy (>=1.0.3)
Requires-Dist: pytumblr
Requires-Dist: pyyaml
Requires-Dist: requests
Requires-Dist: sqlalchemy
Requires-Dist: tweepy
